{"nodes": [{"id": "d_users_sanja_dyad_apps_load_saathi_app_1_osrm_src_hooks_usesmartmatch_ts", "label": "useSmartMatch.ts", "file_type": "code", "source_file": "D:\\Users\\sanja\\dyad-apps\\LOAD-SAATHI-APP-1-OSRM\\src\\hooks\\useSmartMatch.ts", "source_location": "L1"}, {"id": "hooks_usesmartmatch_usesmartmatch", "label": "useSmartMatch()", "file_type": "code", "source_file": "D:\\Users\\sanja\\dyad-apps\\LOAD-SAATHI-APP-1-OSRM\\src\\hooks\\useSmartMatch.ts", "source_location": "L14"}], "edges": [{"source": "d_users_sanja_dyad_apps_load_saathi_app_1_osrm_src_hooks_usesmartmatch_ts", "target": "react", "relation": "imports_from", "confidence": "EXTRACTED", "source_file": "D:\\Users\\sanja\\dyad-apps\\LOAD-SAATHI-APP-1-OSRM\\src\\hooks\\useSmartMatch.ts", "source_location": "L1", "weight": 1.0}, {"source": "d_users_sanja_dyad_apps_load_saathi_app_1_osrm_src_hooks_usesmartmatch_ts", "target": "hooks_usesmartmatch_usesmartmatch", "relation": "contains", "confidence": "EXTRACTED", "source_file": "D:\\Users\\sanja\\dyad-apps\\LOAD-SAATHI-APP-1-OSRM\\src\\hooks\\useSmartMatch.ts", "source_location": "L14", "weight": 1.0}], "raw_calls": [{"caller_nid": "hooks_usesmartmatch_usesmartmatch", "callee": "useState", "is_member_call": false, "source_file": "D:\\Users\\sanja\\dyad-apps\\LOAD-SAATHI-APP-1-OSRM\\src\\hooks\\useSmartMatch.ts", "source_location": "L19"}, {"caller_nid": "hooks_usesmartmatch_usesmartmatch", "callee": "useState", "is_member_call": false, "source_file": "D:\\Users\\sanja\\dyad-apps\\LOAD-SAATHI-APP-1-OSRM\\src\\hooks\\useSmartMatch.ts", "source_location": "L20"}, {"caller_nid": "hooks_usesmartmatch_usesmartmatch", "callee": "useRef", "is_member_call": false, "source_file": "D:\\Users\\sanja\\dyad-apps\\LOAD-SAATHI-APP-1-OSRM\\src\\hooks\\useSmartMatch.ts", "source_location": "L22"}, {"caller_nid": "hooks_usesmartmatch_usesmartmatch", "callee": "useRef", "is_member_call": false, "source_file": "D:\\Users\\sanja\\dyad-apps\\LOAD-SAATHI-APP-1-OSRM\\src\\hooks\\useSmartMatch.ts", "source_location": "L23"}, {"caller_nid": "hooks_usesmartmatch_usesmartmatch", "callee": "useCallback", "is_member_call": false, "source_file": "D:\\Users\\sanja\\dyad-apps\\LOAD-SAATHI-APP-1-OSRM\\src\\hooks\\useSmartMatch.ts", "source_location": "L25"}, {"caller_nid": "hooks_usesmartmatch_usesmartmatch", "callee": "useEffect", "is_member_call": false, "source_file": "D:\\Users\\sanja\\dyad-apps\\LOAD-SAATHI-APP-1-OSRM\\src\\hooks\\useSmartMatch.ts", "source_location": "L49"}]}