{"nodes": [{"id": "d_users_sanja_dyad_apps_load_saathi_app_1_osrm_src_components_breadcrumbs_tsx", "label": "Breadcrumbs.tsx", "file_type": "code", "source_file": "D:\\Users\\sanja\\dyad-apps\\LOAD-SAATHI-APP-1-OSRM\\src\\components\\Breadcrumbs.tsx", "source_location": "L1"}], "edges": [{"source": "d_users_sanja_dyad_apps_load_saathi_app_1_osrm_src_components_breadcrumbs_tsx", "target": "react_router_dom", "relation": "imports_from", "confidence": "EXTRACTED", "source_file": "D:\\Users\\sanja\\dyad-apps\\LOAD-SAATHI-APP-1-OSRM\\src\\components\\Breadcrumbs.tsx", "source_location": "L1", "weight": 1.0}, {"source": "d_users_sanja_dyad_apps_load_saathi_app_1_osrm_src_components_breadcrumbs_tsx", "target": "lucide_react", "relation": "imports_from", "confidence": "EXTRACTED", "source_file": "D:\\Users\\sanja\\dyad-apps\\LOAD-SAATHI-APP-1-OSRM\\src\\components\\Breadcrumbs.tsx", "source_location": "L2", "weight": 1.0}], "raw_calls": []}