{"nodes": [{"id": "d_users_sanja_dyad_apps_load_saathi_app_1_osrm_src_theme_theme_tsx", "label": "theme.tsx", "file_type": "code", "source_file": "D:\\Users\\sanja\\dyad-apps\\LOAD-SAATHI-APP-1-OSRM\\src\\theme\\theme.tsx", "source_location": "L1"}, {"id": "theme_theme_usetheme", "label": "useTheme()", "file_type": "code", "source_file": "D:\\Users\\sanja\\dyad-apps\\LOAD-SAATHI-APP-1-OSRM\\src\\theme\\theme.tsx", "source_location": "L54"}], "edges": [{"source": "d_users_sanja_dyad_apps_load_saathi_app_1_osrm_src_theme_theme_tsx", "target": "react", "relation": "imports_from", "confidence": "EXTRACTED", "source_file": "D:\\Users\\sanja\\dyad-apps\\LOAD-SAATHI-APP-1-OSRM\\src\\theme\\theme.tsx", "source_location": "L1", "weight": 1.0}, {"source": "d_users_sanja_dyad_apps_load_saathi_app_1_osrm_src_theme_theme_tsx", "target": "theme_theme_usetheme", "relation": "contains", "confidence": "EXTRACTED", "source_file": "D:\\Users\\sanja\\dyad-apps\\LOAD-SAATHI-APP-1-OSRM\\src\\theme\\theme.tsx", "source_location": "L54", "weight": 1.0}], "raw_calls": [{"caller_nid": "theme_theme_usetheme", "callee": "useContext", "is_member_call": false, "source_file": "D:\\Users\\sanja\\dyad-apps\\LOAD-SAATHI-APP-1-OSRM\\src\\theme\\theme.tsx", "source_location": "L54"}]}